gaikwad411_greet/__init__.py
gaikwad411_greet/__main__.py
gaikwad411_greet/config.cfg
gaikwad411_greet/test_utils.py
gaikwad411_greet/utils.py
gaikwad411_greet-1.7.0.dist-info/LICENSE.txt
gaikwad411_greet-1.7.0.dist-info/METADATA
gaikwad411_greet-1.7.0.dist-info/WHEEL
gaikwad411_greet-1.7.0.dist-info/entry_points.txt
gaikwad411_greet-1.7.0.dist-info/top_level.txt
gaikwad411_greet-1.7.0.dist-info/RECORD
