Metadata-Version: 2.1
Name: gaikwad411-greet
Version: 1.7.0
Summary: Greets the world in old stupid way
Home-page: https://github.com/gaikwad411/gaikwad411_greet
Author: Sachin Gaikwad
Author-email: gaikwad411@gmail.com
License: MIT
Platform: UNKNOWN
Classifier: License :: OSI Approved :: MIT License
Classifier: Programming Language :: Python
Classifier: Programming Language :: Python :: 3
